{
  "aor": 0.0010920689655172413,
  "aqi": 0.0026030015862068966,
  "bids_meta": {
    "AcquisitionDuration": 362.5,
    "DelayTime": 0.8,
    "RepetitionTime": 2.5,
    "TaskName": "categorization",
    "dataset": "ds003764",
    "modality": "bold",
    "run_id": 3,
    "session_id": "01",
    "subject_id": "07",
    "task_id": "categorization"
  },
  "dummy_trs": 0,
  "dvars_nstd": 14.972683873263886,
  "dvars_std": 1.0674749652083333,
  "dvars_vstd": 1.0151417768055557,
  "efc": 0.5130281216996183,
  "fber": 3074.527099609375,
  "fd_mean": 0.06618181244569465,
  "fd_num": 6,
  "fd_perc": 4.137931034482759,
  "fwhm_avg": 1.9430855359077996,
  "fwhm_x": 1.899428442040277,
  "fwhm_y": 2.1958085714285716,
  "fwhm_z": 1.7340195942545507,
  "gcor": 0.0209309,
  "gsr_x": -0.00666926521807909,
  "gsr_y": 0.023892635479569435,
  "provenance": {
    "md5sum": "2e054297c71e52db98663e7b374bfa97",
    "settings": {
      "fd_thres": 0.2,
      "testing": false
    },
    "software": "mriqc",
    "version": "22.0.6",
    "webapi_port": null,
    "webapi_url": "https://mriqc.nimh.nih.gov/api/v1"
  },
  "size_t": 145,
  "size_x": 64,
  "size_y": 64,
  "size_z": 31,
  "snr": 6.403692228949361,
  "spacing_tr": 2.5,
  "spacing_x": 3.500000238418579,
  "spacing_y": 3.5,
  "spacing_z": 3.5000181198120117,
  "summary_bg_k": 21.45649000642597,
  "summary_bg_mad": 9.164778368342262,
  "summary_bg_mean": 59.72024154663086,
  "summary_bg_median": 22.188199996948242,
  "summary_bg_n": 76346.0,
  "summary_bg_p05": 14.839085817337036,
  "summary_bg_p95": 277.5218505859375,
  "summary_bg_stdv": 110.35309600830078,
  "summary_fg_k": 0.9082425805745444,
  "summary_fg_mad": 174.5194019884549,
  "summary_fg_mean": 1253.302734375,
  "summary_fg_median": 1238.3916015625,
  "summary_fg_n": 23528.0,
  "summary_fg_p05": 970.0292816162109,
  "summary_fg_p95": 1605.2863647460938,
  "summary_fg_stdv": 193.3830108642578,
  "tsnr": 101.69979095458984
}