{
  "aor": 0.003937655172413792,
  "aqi": 0.006660398344827586,
  "bids_meta": {
    "AcquisitionDuration": 362.5,
    "DelayTime": 0.8,
    "RepetitionTime": 2.5,
    "TaskName": "categorization",
    "dataset": "ds003764",
    "modality": "bold",
    "run_id": 1,
    "session_id": "01",
    "subject_id": "14",
    "task_id": "categorization"
  },
  "dummy_trs": 0,
  "dvars_nstd": 20.14706313611111,
  "dvars_std": 1.179323247638889,
  "dvars_vstd": 1.0408763607638885,
  "efc": 0.5588076999091013,
  "fber": 1909.3802490234375,
  "fd_mean": 0.08612829153098822,
  "fd_num": 9,
  "fd_perc": 6.206896551724138,
  "fwhm_avg": 1.8801414548159634,
  "fwhm_x": 1.7789201211793164,
  "fwhm_y": 2.039099861097345,
  "fwhm_z": 1.8224043821712286,
  "gcor": 0.0125291,
  "gsr_x": 0.004771588370203972,
  "gsr_y": 0.03340056166052818,
  "provenance": {
    "md5sum": "9e1e6ebd590d42561240ed003ade9512",
    "settings": {
      "fd_thres": 0.2,
      "testing": false
    },
    "software": "mriqc",
    "version": "22.0.6",
    "webapi_port": null,
    "webapi_url": "https://mriqc.nimh.nih.gov/api/v1"
  },
  "size_t": 145,
  "size_x": 64,
  "size_y": 64,
  "size_z": 31,
  "snr": 6.633873231348202,
  "spacing_tr": 2.5,
  "spacing_x": 3.499999761581421,
  "spacing_y": 3.500000238418579,
  "spacing_z": 3.499739170074463,
  "summary_bg_k": 22.522190438234063,
  "summary_bg_mad": 13.151514307152443,
  "summary_bg_mean": 64.63346862792969,
  "summary_bg_median": 26.003582000732422,
  "summary_bg_n": 70858.0,
  "summary_bg_p05": 15.417742776870728,
  "summary_bg_p95": 271.26425170898415,
  "summary_bg_stdv": 104.94519805908203,
  "summary_fg_k": 0.7678793292701531,
  "summary_fg_mad": 161.15507863369191,
  "summary_fg_mean": 1163.2843017578125,
  "summary_fg_median": 1149.71826171875,
  "summary_fg_n": 28556.0,
  "summary_fg_p05": 915.3871154785156,
  "summary_fg_p95": 1479.5802001953125,
  "summary_fg_stdv": 173.30722045898438,
  "tsnr": 75.61002349853516
}